alma_client/__init__.py
alma_client/api_modes.py
alma_client/async_client.py
alma_client/client.py
alma_client/context.py
alma_client/paginated_results.py
alma_client/request.py
alma_client/response.py
alma_client/version.py
alma_client/credentials/__init__.py
alma_client/credentials/alma_session.py
alma_client/credentials/api_key.py
alma_client/credentials/base.py
alma_client/credentials/merchant_id.py
alma_client/endpoints/__init__.py
alma_client/endpoints/base.py
alma_client/endpoints/exports.py
alma_client/endpoints/merchants.py
alma_client/endpoints/orders.py
alma_client/endpoints/payments.py
alma_client/entities/__init__.py
alma_client/entities/base.py
alma_client/entities/eligibility.py
alma_client/entities/export.py
alma_client/entities/fee_plan.py
alma_client/entities/installment.py
alma_client/entities/merchant.py
alma_client/entities/order.py
alma_client/entities/payment.py
alma_client/entities/refund.py
tests/__init__.py
tests/test_async_requests.py
tests/test_client.py
tests/test_context.py
tests/test_credentials.py
tests/test_request.py
alma_client-3.0.2.dist-info/LICENSE
alma_client-3.0.2.dist-info/METADATA
alma_client-3.0.2.dist-info/WHEEL
alma_client-3.0.2.dist-info/top_level.txt
alma_client-3.0.2.dist-info/RECORD
