Metadata-Version: 2.1
Name: alma-client
Version: 3.0.2
Summary: Python API client for the Alma Installments API
Home-page: https://github.com/alma/alma-python-client
Author: Alma
Author-email: contact@getalma.eu
License: MIT
Classifier: License :: OSI Approved :: MIT License
Classifier: Programming Language :: Python :: 3
Classifier: Programming Language :: Python :: 3.8
Classifier: Programming Language :: Python :: 3.9
Classifier: Programming Language :: Python :: 3.10
License-File: LICENSE
Requires-Dist: httpx
